uzoenr/__init__.py
uzoenr/fb2.py
uzoenr/morpho.py
uzoenr/rss.py
uzoenr/uzoenr.py
uzoenr/zimread.py
uzoenr-15.2.dist-info/COPYING
uzoenr-15.2.dist-info/METADATA
uzoenr-15.2.dist-info/WHEEL
uzoenr-15.2.dist-info/entry_points.txt
uzoenr-15.2.dist-info/top_level.txt
uzoenr-15.2.dist-info/RECORD
