Metadata-Version: 2.1
Name: uzoenr
Version: 15.2
Summary: CLI Web browser
Author: sherekhan
Classifier: Development Status :: 5 - Production/Stable
Classifier: Environment :: Console
Classifier: Intended Audience :: System Administrators
Classifier: License :: OSI Approved :: GNU General Public License v3 or later (GPLv3+)
Classifier: Operating System :: OS Independent
Classifier: Programming Language :: Python :: 3 :: Only
Classifier: Topic :: Internet :: WWW/HTTP :: Browsers
Classifier: Topic :: Utilities
Classifier: Natural Language :: Russian
Requires-Python: >=3.6
License-File: COPYING
Requires-Dist: requests (>=2.22.0)
Requires-Dist: pymorphy2 (>=0.9.1)
Requires-Dist: libzim (>=1.1.1)
